MANIFEST.in
README.md
setup.cfg
setup.py
kubernetes_configmap_sync/__init__.py
kubernetes_configmap_sync/__main__.py
kubernetes_configmap_sync/app.py
kubernetes_configmap_sync.egg-info/PKG-INFO
kubernetes_configmap_sync.egg-info/SOURCES.txt
kubernetes_configmap_sync.egg-info/dependency_links.txt
kubernetes_configmap_sync.egg-info/requires.txt
kubernetes_configmap_sync.egg-info/top_level.txt