Metadata-Version: 2.1
Name: kubernetes-configmap-sync
Version: 1.1.5
Summary: This utility takes a source directory and creates automatically ConfigMap in the Kubernetes cluster                 based on the content of that directory.
Home-page: https://github.com/julb/kubernetes-configmap-sync
Author: Julb
Author-email: julien@julb.me
License: MIT
Platform: UNKNOWN
Classifier: License :: OSI Approved :: MIT License
Classifier: Programming Language :: Python :: 3
Classifier: Programming Language :: Python :: 3.8
